portal/__init__.py
portal/views.py
portal/templates/index.html
portal/templates/navigation_snippet.html
portal/translations/messages.pot
portal/translations/de/LC_MESSAGES/messages.po
portal/translations/en/LC_MESSAGES/messages.po
portal/translations/ru/LC_MESSAGES/message.po
portal/translations/zh_CN/LC_MESSAGES/messages.po
flaskbb_plugin_portal-1.2.0.dist-info/METADATA
flaskbb_plugin_portal-1.2.0.dist-info/WHEEL
flaskbb_plugin_portal-1.2.0.dist-info/entry_points.txt
flaskbb_plugin_portal-1.2.0.dist-info/top_level.txt
flaskbb_plugin_portal-1.2.0.dist-info/RECORD
