Metadata-Version: 2.1
Name: flaskbb-plugin-portal
Version: 1.2.0
Summary: A portal plugin for FlaskBB
Home-page: https://flaskbb.org
Author: FlaskBB Team
Author-email: peter.justin@outlook.com
License: BSD
Project-URL: Code, https://github.com/flaskbb/flaskbb-plugin-portal
Project-URL: Issue Tracker, https://github.com/flaskbb/flaskbb-plugin-portal/issues
Keywords: flaskbb plugin portal
Platform: any
Classifier: Development Status :: 5 - Production/Stable
Classifier: Environment :: Web Environment
Classifier: Environment :: Plugins
Classifier: Framework :: Flask
Classifier: Intended Audience :: Developers
Classifier: License :: OSI Approved :: BSD License
Classifier: Operating System :: OS Independent
Classifier: Programming Language :: Python
Classifier: Programming Language :: Python :: 3
Classifier: Topic :: Internet :: WWW/HTTP :: Dynamic Content
Classifier: Topic :: Software Development :: Libraries :: Python Modules
Requires-Dist: FlaskBB (>=2.1.0)
